squeak/__init__.py
squeak/params.py
squeak/core/__init__.py
squeak/core/elliptic.py
squeak/core/encryption.py
squeak/core/hashing.py
squeak/core/keys.py
squeaklib-0.13.1.dist-info/LICENSE
squeaklib-0.13.1.dist-info/METADATA
squeaklib-0.13.1.dist-info/WHEEL
squeaklib-0.13.1.dist-info/top_level.txt
squeaklib-0.13.1.dist-info/zip-safe
squeaklib-0.13.1.dist-info/RECORD
