Metadata-Version: 2.1
Name: squeaklib
Version: 0.13.1
Summary: Squeak library
Home-page: UNKNOWN
Author: Jonathan Zernik
License: UNKNOWN
Keywords: squeak
Platform: UNKNOWN
Classifier: Programming Language :: Python :: 3
Classifier: Operating System :: OS Independent
License-File: LICENSE
Requires-Dist: cryptography (<3.5,>=3.3.0)
Requires-Dist: python-bitcoinlib (<0.12,>=0.11.0)
Requires-Dist: ECPy (<1.3,>=1.2.0)
